{
  "Calabaza": "Pumpkin",
  "Hervir": "To Boil",
  "Leche Descremada": "Cream Milk",
  "Sabe A": "Tastes Like",
  "Clara": "Egg White",
  "Desafío": "Challenge",
  "Harina": "Flour",
  "Juez": "Judge",
  "Sartén": "Frying Pan",
  "Agrio": "Sour",
  "Costillas": "Ribs",
  "Pelar": "To Peel",
  "Descongelar": "To Thaw",
  "Perejil": "Parsley",
  "Seleccionar": "To Select",
  "Revolver": "To Stir",
  "Comportamiento": "Behaviour",
  "Amargo": "Bitter",
  "En Llamas": "On Fire",
  "Novedades": "New Items",
  "Suscribir": "To Subscribe",
  "Conforme": "Satisfied",
  "Confiable": "Reliable",
  "Globo": "Balloon",
  "Carnicería": "Butchery",
  "Terreno": "Land",
  "Frutal": "Fruit Tree",
  "Cultivar": "To Grow",
  "Calabacines": "Squash",
  "Trigo": "Wheat",
  "Arruinar": "To Ruin",
  "Helada": "Frost",
  "Semilla": "Seed",
  "Se Congela": "To Freeze",
  "Consecuencia": "Consequence",
  "Huerto": "Orchard",
  "Aceituna": "Olive",
  "Bajo Cero": "Below Zero",
  "Evitable": "Avoidable",
  "Coco": "Coconut",
  "Estornudar": "To Sneeze",
  "Fuegos Artificiales": "Fireworks",
  "Janucá": "Hanukkah",
  "Atraer": "To Bring",
  "Judío": "Jewish",
  "Recuerdos": "Souvenirs",
  "Día Festivo": "Holiday",
  "Anciano": "Elderly",
  "Musulmán": "Muslim",
  "Azotea": "Rooftop",
  "Monarquía": "Monarchy",
  "Protestar": "To Protest",
  "Primera Ministra": "Prime Minister",
  "Británico": "British",
  "Embajador": "Ambassador",
  "Partido": "Party",
  "Desarrollar": "To Develop",
  "Huelga": "Strike",
  "Aerolíneas": "Airlines",
  "Respecto": "Regarding",
  "Conferencia De Prensa": "Press Conference",
  "Precio De Venta": "Sale",
  "Gruesa": "Thick",
  "Adecuado": "Suitable",
  "Silla De Ruedas": "Wheelchair",
  "Cuidador": "Caregiver",
  "Discapacidad": "Disability",
  "Aprobar": "Approve",
  "Sin Receta": "Over-The-Counter",
  "Credencia": "Id Card",
  "Sano": "Healthy",
  "Receta": "Prescription",
  "Centro De Salud": "Health Clinic",
  "Peinado": "Hairstyle",
  "A Continuation": "Up Next",
  "Aparece": "To Appear",
  "Estilista": "Stylist",
  "Han Presentado": "Have Introduced",
  "Diseñadores": "Designers",
  "Volviendo Al Tema": "Back To The Topic",
  "Aparecer": "To Appear",
  "Interrumpir": "To Interrupt",
  "Sentido Común": "Common Sense",
  "Insistir": "To Insist",
  "Por Curiosidad": "Out Of Curiosity",
  "Cosmopolita": "Cosmopolitan",
  "Seguro De Salud": "Health Insurance",
  "Atencion Medica": "Health Care",
  "Tarifa": "Price",
  "Solicitar": "To Apply",
  "De Hecho": "In Fact",
  "Cobertura Medica": "Medical Cover",
  "Medicamento": "Medication",
  "Bandeja": "Tray",
  "Decorar": "To Decorate",
  "Persianas": "Blinds",
  "Colgar": "To Hang",
  "Metro De Largo": "Metre Long",
  "Medir": "To Measure",
  "Macetas": "Flower Pots",
  "Aluminio": "Aluminium",
  "Cojines": "Cushions",
  "Banqueta": "Stool",
  "Candelabro": "Candle Holder",
  "Jarrón": "Vase",
  "Colocar": "To Place",
  "Decoración": "Decor",
  "Abrigo De Piel": "Fur Coat",
  "Buscador": "Search Engine",
  "Nombre De Usuario": "Username",
  "Adjuntar": "To Attach",
  "Estafar": "To Scam",
  "Blogueros": "Bloggers",
  "Datos": "Data",
  "Enlace": "Link",
  "Tendencia": "Trending",
  "Símbolo": "Symbol",
  "Innecesarios": "Unnecessary",
  "Teclas": "Keys",
  "Configurar": "To Configure",
  "Presionar": "To Press",
  "Panadero": "Baker",
  "Quedarse Sin Datos": "Run Out Of Data",
  "Desenchufar": "To Unplug",
  "Aproximado": "Approximate",
  "Electricista": "Electrician",
  "Plomero": "Plumber",
  "Mantenimiento": "Maintenance",
  "Calentador": "Heater",
  "Gotera": "Leak",
  "Destornillador": "Screwdriver",
  "Mano De Obra": "Labour",
  "Ferretería": "Hardware Store",
  "Caño": "Pipe",
  "Clavo": "Nail",
  "Martillo": "Hammer",
  "Regar": "To Water",
  "Echar Una Mano": "Lend A Hand",
  "Poner La Mesa": "Set The Table",
  "Mantel": "Tablecloth",
  "Ordenado": "Tidy",
  "Enchufes": "Sockets",
  "Herramientas": "Tools",
  "Marco": "Frame",
  "A La Perfección": "To Perfection",
  "Ambientes": "Rooms",
  "Condición": "Term",
  "Céntrico": "Central",
  "Timbre": "Doorbell",
  "Acogedora": "Welcoming",
  "Fregar": "To Scrub",
  "Al Aire Libre": "Outdoor",
  "Desilusionado": "Disappointed",
  "Cita A Ciegas": "Blind Date",
  "Chiste": "Joke",
  "Anticuado": "Old-Fashioned",
  "Ilusionado": "Hopefully",
  "Educada": "Talkative",
  "O Sea": "In Other Words",
  "Discusión": "Argument",
  "Aquí Mismo": "Right Here",
  "Guisantes": "Peas",
  "Docena": "Dozen",
  "Olla": "Pot",
  "Líquido": "Liquid",
  "Congelador": "Freezer",
  "Espinaca": "Spinach",
  "Yema": "Yolk",
  "Pavo": "Turkey",
  "Cereza": "Cherry",
  "Tarta": "Pie",
  "Chile": "Chilly",
  "Alimentos": "Food",
  "Camarones": "Shrimps",
  "Berenjena": "Aubergine",
  "Centro Médico": "Health Clinic",
  "Bucear": "Scuba Dive",
  "Doloroso": "Painful",
  "Pista": "Track",
  "A Fin De Cuentas": "In The End",
  "Por Lo Menos": "At Least",
  "Aliviado": "Relieved",
  "Avena": "Oatmeal",
  "Calentar": "To Heat",
  "Merendar": "To Have A Snack",
  "Huevos Revueltos": "Scrambled Eggs",
  "Cucharada": "Tablespoon",
  "Guiso": "Stew",
  "Casera": "Homemade",
  "Mantequilla De Maní": "Peanut Butter",
  "Hierba": "Herb",
  "Hoy En Día": "Nowadays",
  "Jugosa": "Juicy",
  "Poco Después": "Shortly After",
  "Artículo": "Item",
  "Delincuente": "Criminal",
  "Delito": "Crime",
  "Cárcel": "Jail",
  "Explotar": "To Explode",
  "Atentado": "Attack",
  "Prsaen": "Press",
  "Denunciar": "To Report",
  "Aguja": "Needle",
  "Periodista": "Journalist",
  "Promedio": "Average",
  "Desaprobar": "To Fail",
  "Atentamente": "Attentively",
  "Unidad": "Unit",
  "Desmayar": "To Faint",
  "Resolver": "To Solve",
  "Embajada": "Embassy",
  "Estacionamiento": "Parking Lot",
  "Laboratorio": "Laboratory",
  "Ramo": "Bouquet",
  "No Hay De Qué": "Not At All",
  "Colegio": "School",
  "Niñero": "Babysitter",
  "Amabilidad": "Kindness",
  "Muy Amable": "How Kind Of You",
  "Por Anticipado": "In Advance",
  "Embotellamiento": "Traffic Jam",
  "Hora Pico": "Rush Hour",
  "Rotonda": "Roundabout",
  "Ciclovía": "Bike Lane",
  "Peatonal": "Pedestrian",
  "Acera": "Sidewalk",
  "Acceso": "Entrance",
  "Diagonales": "Diagonal Streets",
  "Túnel": "Tunnel",
  "Sigue Todo Recto": "Keep Straight",
  "Carril": "Lane",
  "Camiones": "Trucks",
  "Cruce": "Intersection",
  "Caber": "To Fit",
  "Calle Sin Salida": "Dead End Street",
  "Dificultad": "Difficulty",
  "Demanda": "Demand",
  "Esfuerzo": "Effort",
  "Préstamo": "Loan",
  "Inútil": "Useless",
  "Equipos": "Equipment",
  "Disminuir": "To Reduce",
  "Parabrisas": "Windscreen",
  "No Tarde": "Don't Stall",
  "Bombero": "Firefighters",
  "Socorro": "Help",
  "Por Si Acaso": "Just In Case",
  "Ya Mismo": "Right Now",
  "Cerrar Con Llave": "To Lock Up",
  "Robos": "Robberies",
  "De Inmediato": "Immediately",
  "Dentro De": "Within A",
  "Internal": "To Admit",
  "Urgentemente": "Urgently",
  "Fallecer": "To Die",
  "Seguro Medicino": "Health Insurance",
  "Chocar": "To Crash",
  "Tratamiento": "Treatment",
  "Estricto": "Strict",
  "Estornudiar": "To Sneeze",
  "Enfermedad": "Illness",
  "Radiografía": "X-Ray",
  "Muela": "Molar",
  "Parto": "Birth",
  "Consultario": "Office",
  "Capacitacion": "Training",
  "propietario": "Owner",
  "Envidioso": "Envious",
  "Encantador": "Charming",
  "Sensata": "Sensible",
  "Inseguro": "Insecure",
  "Comprometido": "Engaged",
  "Sugerencia": "Recommendation",
  "Cuánto Antes": "As Soon As Possible",
  "Compacitación": "Training",
  "Felizmente": "Happily",
  "Estar En Contacto": "To Be In Contact",
  "Obligatorio": "Mandatory",
  "Carta De Presentación": "Cover Letter",
  "Rechazar": "To Refuse",
  "Escáner": "Scanner",
  "Recursos": "Resources",
  "Aproximadamente": "Approximately",
  "Cualidad": "Quality",
  "Alcalde": "Mayor",
  "Intercambiar": "Exchange",
  "Pensamiento": "Thought",
  "Político": "Politician",
  "Ciudadanos": "Citizens",
  "Impuesto": "Tax",
  "Minoría": "Minority",
  "Reconocer": "To Admit",
  "Política": "Politics",
  "Absolutamente": "Absolutely",
  "Presupuesto": "Budget",
  "Ministro": "Minister",
  "Embarcar": "To Board",
  "Aterrizar": "To Land",
  "Despegar": "Lift Off",
  "Escalas": "Layovers",
  "Viajeros": "Travellers",
  "Bañarse": "To Swim",
  "Manzana": "Apple",
  "Hospedarse": "To Stay",
  "Juventud": "Youth",
  "A Horario": "On Schedule",
  "De Ida": "One Way",
  "Retrato": "Portrait",
  "Subtítulos": "Subtitles",
  "Celebridades": "Celebrities",
  "Presentador": "Host",
  "Entrevistar": "To Interview",
  "Estreno": "Premiere",
  "Espectadores": "Spectators",
  "Anterior": "Previous",
  "Escultor": "Sculptor",
  "Desconocido": "Unknown",
  "Aplaudir": "To Applaud",
  "Autorretrato": "Self-Portrait",
  "Suelta": "Loose",
  "Chaleco": "Vest",
  "Saco": "Coat",
  "Lino": "Linen",
  "Aros": "Earrings",
  "Colorido": "Colorful",
  "Joyería": "Jewelry Store",
  "Gangas": "Deals",
  "Cordones": "Shoelaces",
  "Atar": "To Tie",
  "Etiqueta": "Tag",
  "Manga": "Sleeve",
  "Pantuflas": "Slippers",
  "Tejer": "To Knit",
  "Crema Corporal": "Body Cream",
  "Desodorante": "Deodorant",
  "Protector Solar": "Sunscreen",
  "Afeitar": "To Shave",
  "Peluquero": "Hairdresser",
  "Rizado": "Curly",
  "Afeitadora": "Shaver",
  "Secador De Pelo": "Hair Dryer",
  "Peluquería": "Hair Salon",
  "Uñas": "Nails",
  "Cortauñas": "Nail Cutter",
  "Esmalte De Uñas": "Nail Polish",
  "Pañuelo": "Tissue",
  "Lápiz Labial": "Lipstick",
  "Cantidad": "Quantity",
  "Salón De Belleza": "Beauty Salon",
  "Colonia": "Cologne",
  "Rebajada": "Sales",
  "Hebilla": "Buckle",
  "Chal": "Shawl",
  "Raya": "Stripe",
  "Cobrar": "To Charge",
  "Claro": "Light",
  "Plateado": "Of Silver",
  "Cuantas": "A Few",
  "Floreada": "Flower Print",
  "Reparación": "Repair",
  "Garantía": "Warranty",
  "Bombilla": "Bulb",
  "Prender": "Turn On",
  "Vidrio": "Glass",
  "Enseguida": "Right Away",
  "Radiador": "Heater",
  "Si No": "Otherwise",
  "Bañera": "Bathtub",
  "Devoluciones": "Returns",
  "Realizar": "To Carry Out",
  "Electrodomésticos": "Appliances",
  "Servilleta": "Napkin",
  "Tocino": "Bacon",
  "Cubiertos": "Silverware",
  "Mariscos": "Shellfish",
  "Bien Cocido": "Well Done",
  "Cordero": "Lamb",
  "Carne De Res": "Beef",
  "Chuletas De Cerdo": "Pork Chops",
  "Manzanilla": "Chamomile",
  "Agua Con Gas": "Carbonated Water",
  "Una Queja": "A Complaint",
  "Atención": "Service",
  "Reclamo": "Claim",
  "Actitud": "Attitude",
  "En Cuanto": "As Soon As",
  "Rastrear": "To Track",
  "Una Vez": "Once",
  "Envío": "Shipping",
  "Un Pedido": "An Order",
  "Gastos": "Costs",
  "La Devolución": "The Return",
  "Vencido": "Expired",
  "Reemplazar": "Replace",
  "Quinto": "Fifth",
  "En Primer Lugar": "First Of All",
  "Parecida": "Similar",
  "Fijar": "To Check",
  "En Cualquier Caso": "In Any Case",
  "Comparar": "To Compare",
  "Encargarse": "To Handle",
  "Agotado": ["Sold Out", "Exhausted"],
  "Periodo": "Period",
  "Plazo": "Period",
  "Parientes": "Relatives",
  "Natal": "Native",
  "Por Lo General": "In General",
  "Vecindario": "Neighborhood",
  "Vida Nocturna": "Nightlife",
  "Arroyo": "Stream",
  "Ola": "Wave",
  "Cultivos": "Crops",
  "Bahía": "Bay",
  "Medio Ambiente": "Environment",
  "Tortuga": "Tortoise",
  "Ave": "Bird",
  "Selva": "Jungle",
  "Pingüino": "Penguin",
  "Por Su Parte": "He For One",
  "Ventas": "Sales",
  "Principalmente": "Mainly",
  "Preferible": "Preferably",
  "Lograr": "To Achieve",
  "En Cuento": "As Far As",
  "Revisar": "To Review",
  "Contrato": "Contract",
  "Portero": ["Goalkeeper", "Doorman"],
  "Entrenador": "Coach",
  "Pegar": ["To Hit", "To Glue"],
  "Tirar": "To Throw",
  "Patear": "To Kick",
  "Penales": "Penalties",
  "Echar": "To Throw Out",
  "Suavemente": "Softly",
  "Arco": "Goal",
  "Atrapar": "To Catch",
  "Atajar": "To Intercept",
  "Apenas": "Barely",
  "Maletín": "Briefcase",
  "Portar": "To Behave",
  "Pulsera": "Bracelet",
  "Ansiosa": "Excited",
  "Sugerir": "To Suggest",
  "Sentido Del Humor": "Sense Of Humour",
  "Prioridad": "Priority",
  "Sino": "But Instead",
  "Un Mago": "A Magician",
  "Gripe": "Flu",
  "Resfriado": "Cold",
  "Deletrear": "To Spell",
  "Tontería": "Nonsense",
  "Opuesto": "Opposite",
  "A pesar De": "Opposite",
  "Estar En Desacuerdo": "To Disagree",
  "Para Nada": "At All",
  "Templado": "Template",
  "Pronóstico": " Forecast",
  "Humedad": "Humidity",
  "Truenos": "Thunder",
  "Tormenta Eléctrica": "Thunderstorm",
  "Inundaciones": "Floods",
  "Nevada": "Snowfall",
  "Tronar": "To Thunder",
  "Lloviznar": "To Drizzle",
  "Neblina": "Fog",
  "Granizo": "Hail",
  "Despejar": "To Clear",
  "Infarto": "Heart Attack",
  "Temporal": "Storm",
  "Sucursal": "Branch",
  "Billete": "BIll",
  "Cajero": "Teller",
  "Monedas": "Coins",
  "Requisitos": "Requirements",
  "Una Transferencia": "A Transfer",
  "Saldo": "Balance",
  "Ahorros": "Savings",
  "Contador": "Accountant",
  "Impresionante":  "Impressive",
  "Capítulo": "Chapter",
  "Contemporáneo": "Contemporary",
  "Entretenido": "Entertained",
  "Entretenidos": "Entertained",
  "Orquesta": "Orchestra",
  "Documentales": "Documentaries",
  "Pasillo":  "Hallway",
  "Conseguir ": "To Get",
  "Marcar": "To Score",
  "Hincha": "Fan",
  "Empatar": "To Draw",
  "Despedir": "To Say Goodbye",
  "A Propósito": "On Purpose",
  "Competidores": "Competitors",
  "Sandalias": "Sandals",
  "Entrenamiento": "Practice",
  "Cancha": "Field",
  "Ponerse De Pie": "To Stand Up",
  "Ventaja": "Advantage",
  "Tránsito": "Traffic",
  "Antiguo": "Ancient",
  "Arriesgar": "To Risk",
  "Esmoquin": "Tuxedo",
  "Asignatura": "Subject",
  "Uvas": "Grapes",
  "Jubilado": "Retired",
  "Alguna Vez": "Ever",
  "Incendio": "Destructive Fire",
  "Campeonato": "Championship",
  "Desempleo": "Unemployment",
  "Medidas": ["Measures", "Measurements"],
  "Cirujana": "Surgeon",
  "Alquilar": "To Rent",
  "Ahorrar": "To Save",
  "Pedir Prestado": "To Borrow",
  "Repaso": "Review",
  "Beca": "Scholarship",
  "Materias": "Classes",
  "Cuanto Antes": "As Soon As Possible",
  "Inscribirse": "Sign Up",
  "Solicitudes": "Applications",
  "Repasar": "To Review",
  "No Es Para Tanto": "No Big Deal",
  "Lentejas": "Lentils",
  "Pepino": "Cucumber",
  "Sabrosa": "Flavourful",
  "Cruda": "Raw",
  "Cuarta": "Fourth",
  "Alojamiento": "Lodging",
  "Paisaje": "Scenery",
  "Liso": "Smooth",
  "En Vez De": "Instead Of",
  "Ubicación": "Location",
  "En Familia": "As A Family",
  "Esculturas": "Sculptures",
  "Marca": "Brand",
  "Semáforos": "Traffic Lights",
  "Enchufar": "To Connect",
  "Auriculares": "Headphones",
  "Navegador": "Browser",
  "Arreglar": "To Fix",
  "Técnicos": "Technicians",
  "Viudo": "Widower",
  "Socio": "Business Partner",
  "Cuadro": "Painting",
  "Conversadora": "Talkative",
  "Callada": "Quiet",
  "Alegre": "Cheerful",
  "Deprimido": "Depressed",
  "Extrovertidos": "Extroverts",
  "Húmedo": "Humid",
  "Cansador": "Tiring",
  "Puntual": "Punctual",
  "Escena": "Scene",
  "Un Paseo": "A Walk",
  "Tercios": "Thirds",
  "Empresarios": "Businesspeople",
  "Vestíbulo": "Lobby",
  "Andén": "Platform",
  "Salón": "Hall",
  "Trozos": "Pieces",
  "Patada": "Kick",
  "Pertenecer": "To Belong",
  "Parlante": "Speaker",
  "Rebanadas": "Slices",
  "Treseo": "Back",
  "Muebles": "Furniture",
  "Pantalla": "Screen",
  "Sin Embargo": "However",
  "Bufanda": "Scarf",
  "A La Venta": "For Sale",
  "Propina": "Tip",
  "Informe": "Report",
  "Aumentar":   "To Increase",
  "Consultar": "To Consult",
  "Contratar": "To Hire",
  "Entregar": "To Deliver",
  "Renunciar": "To Quit"
}